hf_for_legal/__init__.py
hf_for_legal/_decorators.py
hf_for_legal/_logger.py
hf_for_legal/datasets.py
hf_for_legal-0.0.13.dist-info/LICENSE
hf_for_legal-0.0.13.dist-info/METADATA
hf_for_legal-0.0.13.dist-info/WHEEL
hf_for_legal-0.0.13.dist-info/top_level.txt
hf_for_legal-0.0.13.dist-info/RECORD
