Metadata-Version: 2.1
Name: hf-for-legal
Version: 0.0.13
Summary: HF for Legal: A Community Package for Legal Applications 🤗
Home-page: https://github.com/louisbrulenaudet/hf-for-legal
Author: Louis Brulé Naudet
Author-email: louisbrulenaudet@icloud.com
License: Apache License 2.0
Keywords: language-models,retrieval,web-scraping,gpl,nlp,hf-for-legal,machine-learning,retrieval-augmented-generation,RAG,huggingface,generative-ai,llama,Mistral,inference-api,datasets,llm-as-judge
Classifier: Programming Language :: Python
Classifier: Programming Language :: Python :: 3
Classifier: Intended Audience :: Developers
Classifier: Intended Audience :: Science/Research
Classifier: Topic :: Scientific/Engineering :: Artificial Intelligence
Classifier: Topic :: Software Development
Classifier: Topic :: Software Development :: Libraries
Classifier: Topic :: Software Development :: Libraries :: Python Modules
License-File: LICENSE
Provides-Extra: dev
Requires-Dist: pytest ; extra == 'dev'
